507_project/picorv32_pcpi_vec.v
module picorv32_pcpi_vec (
    input clk,
    input resetn,

    input        pcpi_valid,
    input [31:0] pcpi_insn,
    input [31:0] pcpi_rs1,
    input [31:0] pcpi_rs2,

    output reg        pcpi_wr,
    output reg [31:0] pcpi_rd,
    output reg        pcpi_wait,
    output reg        pcpi_ready
);

    wire [6:0] opcode = pcpi_insn[6:0];
    wire [2:0] funct3 = pcpi_insn[14:12];
    wire [6:0] funct7 = pcpi_insn[31:25];

    // Use custom-0 opcode: 0001011
    wire is_custom0 = (opcode == 7'b0001011);

    // Simple operation decode
    wire instr_vadd8 = is_custom0 && (funct3 == 3'b000) && (funct7 == 7'b0000000);
    wire instr_vsub8 = is_custom0 && (funct3 == 3'b001) && (funct7 == 7'b0000000);
    wire instr_vand  = is_custom0 && (funct3 == 3'b010) && (funct7 == 7'b0000000);
    wire instr_vor   = is_custom0 && (funct3 == 3'b011) && (funct7 == 7'b0000000);

    wire instr_vec = instr_vadd8 || instr_vsub8 || instr_vand || instr_vor;

    wire [7:0] a0 = pcpi_rs1[7:0];
    wire [7:0] a1 = pcpi_rs1[15:8];
    wire [7:0] a2 = pcpi_rs1[23:16];
    wire [7:0] a3 = pcpi_rs1[31:24];

    wire [7:0] b0 = pcpi_rs2[7:0];
    wire [7:0] b1 = pcpi_rs2[15:8];
    wire [7:0] b2 = pcpi_rs2[23:16];
    wire [7:0] b3 = pcpi_rs2[31:24];

    wire [31:0] result_vadd8 = {
        a3 + b3,
        a2 + b2,
        a1 + b1,
        a0 + b0
    };

    wire [31:0] result_vsub8 = {
        a3 - b3,
        a2 - b2,
        a1 - b1,
        a0 - b0
    };

    wire [31:0] result_vand = pcpi_rs1 & pcpi_rs2;
    wire [31:0] result_vor  = pcpi_rs1 | pcpi_rs2;

    always @(posedge clk) begin
        if (!resetn) begin
            pcpi_wr    <= 0;
            pcpi_rd    <= 0;
            pcpi_wait  <= 0;
            pcpi_ready <= 0;
        end else begin
            pcpi_wr    <= 0;
            pcpi_ready <= 0;
            pcpi_wait  <= 0;

            if (pcpi_valid && instr_vec) begin
                pcpi_wr    <= 1;
                pcpi_ready <= 1;
                pcpi_wait  <= 0;

                if (instr_vadd8)
                    pcpi_rd <= result_vadd8;
                else if (instr_vsub8)
                    pcpi_rd <= result_vsub8;
                else if (instr_vand)
                    pcpi_rd <= result_vand;
                else if (instr_vor)
                    pcpi_rd <= result_vor;
                else
                    pcpi_rd <= 32'h00000000;
            end
        end
    end

endmodule

507_project/tb_pcpi_vec.v
`timescale 1ns / 1ps

module tb_pcpi_vec;

    reg clk;
    reg resetn;

    reg        pcpi_valid;
    reg [31:0] pcpi_insn;
    reg [31:0] pcpi_rs1;
    reg [31:0] pcpi_rs2;

    wire        pcpi_wr;
    wire [31:0] pcpi_rd;
    wire        pcpi_wait;
    wire        pcpi_ready;

    // Instantiate vector PCPI module
    picorv32_pcpi_vec uut (
        .clk(clk),
        .resetn(resetn),

        .pcpi_valid(pcpi_valid),
        .pcpi_insn(pcpi_insn),
        .pcpi_rs1(pcpi_rs1),
        .pcpi_rs2(pcpi_rs2),

        .pcpi_wr(pcpi_wr),
        .pcpi_rd(pcpi_rd),
        .pcpi_wait(pcpi_wait),
        .pcpi_ready(pcpi_ready)
    );

    // Clock generation
    always begin
        #5 clk = ~clk;
    end

    // Build custom instruction
    // opcode = custom-0 = 0001011
    function [31:0] make_instr;
        input [6:0] funct7;
        input [2:0] funct3;
        begin
            make_instr = {funct7, 5'd2, 5'd1, funct3, 5'd3, 7'b0001011};
        end
    endfunction

    initial begin
        $dumpfile("tb_pcpi_vec.vcd");
        $dumpvars(0, tb_pcpi_vec);

        clk = 0;
        resetn = 0;

        pcpi_valid = 0;
        pcpi_insn  = 32'h00000000;
        pcpi_rs1   = 32'h00000000;
        pcpi_rs2   = 32'h00000000;

        #20;
        resetn = 1;

        // -------------------------
        // Test 1: VADD8
        // rs1 = 01 02 03 04
        // rs2 = 05 06 07 08
        // result = 06 08 0A 0C
        // -------------------------
        pcpi_valid = 1;
        pcpi_insn  = make_instr(7'b0000000, 3'b000);
        pcpi_rs1   = 32'h01020304;
        pcpi_rs2   = 32'h05060708;

        #10;
        if (pcpi_ready && pcpi_wr && pcpi_rd == 32'h06080A0C)
            $display("Test 1 VADD8 passed");
        else
            $display("Test 1 VADD8 failed: pcpi_rd = %h", pcpi_rd);

        pcpi_valid = 0;
        #10;

        // -------------------------
        // Test 2: VSUB8
        // rs1 = 09 08 07 06
        // rs2 = 01 02 03 04
        // result = 08 06 04 02
        // -------------------------
        pcpi_valid = 1;
        pcpi_insn  = make_instr(7'b0000000, 3'b001);
        pcpi_rs1   = 32'h09080706;
        pcpi_rs2   = 32'h01020304;

        #10;
        if (pcpi_ready && pcpi_wr && pcpi_rd == 32'h08060402)
            $display("Test 2 VSUB8 passed");
        else
            $display("Test 2 VSUB8 failed: pcpi_rd = %h", pcpi_rd);

        pcpi_valid = 0;
        #10;

        // -------------------------
        // Test 3: VAND
        // -------------------------
        pcpi_valid = 1;
        pcpi_insn  = make_instr(7'b0000000, 3'b010);
        pcpi_rs1   = 32'hFF00FF00;
        pcpi_rs2   = 32'h0F0F0F0F;

        #10;
        if (pcpi_ready && pcpi_wr && pcpi_rd == 32'h0F000F00)
            $display("Test 3 VAND passed");
        else
            $display("Test 3 VAND failed: pcpi_rd = %h", pcpi_rd);

        pcpi_valid = 0;
        #10;

        // -------------------------
        // Test 4: VOR
        // -------------------------
        pcpi_valid = 1;
        pcpi_insn  = make_instr(7'b0000000, 3'b011);
        pcpi_rs1   = 32'hFF00FF00;
        pcpi_rs2   = 32'h0F0F0F0F;

        #10;
        if (pcpi_ready && pcpi_wr && pcpi_rd == 32'hFF0FFF0F)
            $display("Test 4 VOR passed");
        else
            $display("Test 4 VOR failed: pcpi_rd = %h", pcpi_rd);

        pcpi_valid = 0;
        #10;

        // -------------------------
        // Test 5: Invalid instruction
        // Should not respond
        // -------------------------
        pcpi_valid = 1;
        pcpi_insn  = 32'h00000033;   // normal R-type opcode, not custom-0
        pcpi_rs1   = 32'h11111111;
        pcpi_rs2   = 32'h22222222;

        #10;
        if (!pcpi_ready && !pcpi_wr)
            $display("Test 5 invalid instruction passed");
        else
            $display("Test 5 invalid instruction failed");

        pcpi_valid = 0;
        #10;

        $display("PCPI vector unit testbench finished");
        $finish;
    end

endmodule

507_project/tb_pcpi_vec.vcd
$date
	Wed Apr 29 13:04:08 2026
$end
$version
	Icarus Verilog
$end
$timescale
	1ps
$end
$scope module tb_pcpi_vec $end
$var wire 1 ! pcpi_wr $end
$var wire 1 " pcpi_wait $end
$var wire 1 # pcpi_ready $end
$var wire 32 $ pcpi_rd [31:0] $end
$var reg 1 % clk $end
$var reg 32 & pcpi_insn [31:0] $end
$var reg 32 ' pcpi_rs1 [31:0] $end
$var reg 32 ( pcpi_rs2 [31:0] $end
$var reg 1 ) pcpi_valid $end
$var reg 1 * resetn $end
$scope function make_instr $end
$var reg 3 + funct3 [2:0] $end
$var reg 7 , funct7 [6:0] $end
$upscope $end
$scope module uut $end
$var wire 1 % clk $end
$var wire 1 - instr_vadd8 $end
$var wire 1 . instr_vand $end
$var wire 1 / instr_vec $end
$var wire 1 0 instr_vor $end
$var wire 1 1 instr_vsub8 $end
$var wire 32 2 pcpi_insn [31:0] $end
$var wire 32 3 pcpi_rs1 [31:0] $end
$var wire 32 4 pcpi_rs2 [31:0] $end
$var wire 1 ) pcpi_valid $end
$var wire 1 * resetn $end
$var wire 32 5 result_vand [31:0] $end
$var wire 32 6 result_vor [31:0] $end
$var wire 32 7 result_vsub8 [31:0] $end
$var wire 32 8 result_vadd8 [31:0] $end
$var wire 7 9 opcode [6:0] $end
$var wire 1 : is_custom0 $end
$var wire 7 ; funct7 [6:0] $end
$var wire 3 < funct3 [2:0] $end
$var wire 8 = b3 [7:0] $end
$var wire 8 > b2 [7:0] $end
$var wire 8 ? b1 [7:0] $end
$var wire 8 @ b0 [7:0] $end
$var wire 8 A a3 [7:0] $end
$var wire 8 B a2 [7:0] $end
$var wire 8 C a1 [7:0] $end
$var wire 8 D a0 [7:0] $end
$var reg 32 E pcpi_rd [31:0] $end
$var reg 1 # pcpi_ready $end
$var reg 1 " pcpi_wait $end
$var reg 1 ! pcpi_wr $end
$upscope $end
$upscope $end
$enddefinitions $end
$comment Show the parameter values. $end
$dumpall
$end
#0
$dumpvars
bx E
b0 D
b0 C
b0 B
b0 A
b0 @
b0 ?
b0 >
b0 =
b0 <
b0 ;
0:
b0 9
b0 8
b0 7
b0 6
b0 5
b0 4
b0 3
b0 2
01
00
0/
0.
0-
bx ,
bx +
0*
0)
b0 (
b0 '
b0 &
0%
bx $
x#
x"
x!
$end
#5000
0#
0"
b0 $
b0 E
0!
1%
#10000
0%
#15000
1%
#20000
1/
1-
b1000 @
b111 ?
b110 >
b101 =
b1000000100000001100000000 5
b101000001100000011100001100 6
b100 D
b11 C
b10 B
b110000010000000101000001100 8
b11111100111111001111110011111100 7
b1 A
1:
b1011 9
0%
b101000001100000011100001000 (
b101000001100000011100001000 4
b1000000100000001100000100 '
b1000000100000001100000100 3
b1000001000000110001011 &
b1000001000000110001011 2
b0 ,
b0 +
1)
1*
#25000
b110000010000000101000001100 $
b110000010000000101000001100 E
1#
1!
1%
#30000
0%
0)
#35000
0#
0!
1%
#40000
0-
11
b100 @
b11 ?
b10 >
b1 =
b1000000000000001100000100 5
b1001000010100000011100000110 6
b110 D
b111 C
b1000 B
b1010000010100000101000001010 8
b1000000001100000010000000010 7
b1001 A
b1 <
0%
b1000000100000001100000100 (
b1000000100000001100000100 4
b1001000010000000011100000110 '
b1001000010000000011100000110 3
b1000001001000110001011 &
b1000001001000110001011 2
b1 +
1)
#45000
b1000000001100000010000000010 $
b1000000001100000010000000010 E
1#
1!
1%
#50000
0%
0)
#55000
0#
0!
1%
#60000
01
1.
b1111 @
b1111 ?
b1111 >
b1111 =
b1111000000000000111100000000 5
b11111111000011111111111100001111 6
b0 D
b11111111 C
b0 B
b1110000011110000111000001111 8
b11110000111100011111000011110001 7
b11111111 A
b10 <
0%
b1111000011110000111100001111 (
b1111000011110000111100001111 4
b11111111000000001111111100000000 '
b11111111000000001111111100000000 3
b1000001010000110001011 &
b1000001010000110001011 2
b10 +
1)
#65000
b1111000000000000111100000000 $
b1111000000000000111100000000 E
1#
1!
1%
#70000
0%
0)
#75000
0#
0!
1%
#80000
0.
10
b11 <
0%
b1000001011000110001011 &
b1000001011000110001011 2
b11 +
1)
#85000
b11111111000011111111111100001111 $
b11111111000011111111111100001111 E
1#
1!
1%
#90000
0%
0)
#95000
0#
0!
1%
#100000
0/
00
b100010 @
b100010 ?
b100010 >
b100010 =
b0 5
b110011001100110011001100110011 6
b10001 D
b10001 C
b10001 B
b110011001100110011001100110011 8
b11101111111011111110111111101111 7
b10001 A
0:
b110011 9
b0 <
0%
b100010001000100010001000100010 (
b100010001000100010001000100010 4
b10001000100010001000100010001 '
b10001000100010001000100010001 3
b110011 &
b110011 2
1)
#105000
1%
#110000
0%
0)
